{
   "tracks" : [
      {
         "storeClass" : "GA4GHViewer/Store/SeqFeature/1000genomes",
         "type" : "CanvasFeatures",
         "label" : "1000 Cannabis Strains variants",
         "apiKey": "?key=AIzaSyBrhrnOHsPahYDy1dVzVq1lXlKBSJtCJmU",
         "google": true,
         "style": {
             "featureScale": 0.5
         },
         "maxHeight": 1000,
         "callSetIds" : [],
         "variantSetId": "17527604790083478309",
         "urlTemplate" : "https://genomics.googleapis.com/v1"
      }
   ],
   "highResolutionMode" : 2,
   "plugins" : [
      {
          "location" : "https://rawgit.com/elsiklab/ga4ghviewer/master",
          "name" : "GA4GHViewer"
      }
   ],
   "refSeqOrder": "length descending",
   "classicMenu": true
}
